fgex/__init__.py
fgex/__main__.py
fgex-3.4.11.dist-info/METADATA
fgex-3.4.11.dist-info/WHEEL
fgex-3.4.11.dist-info/top_level.txt
fgex-3.4.11.dist-info/RECORD
