Metadata-Version: 2.4
Name: fgex
Version: 3.4.11
Summary: Firegex client
Home-page: https://github.com/pwnzer0tt1/firegex
Author: Pwnzer0tt1
Author-email: pwnzer0tt1@poliba.it
Classifier: Programming Language :: Python :: 3
Classifier: License :: OSI Approved :: GNU General Public License v3 or later (GPLv3+)
Classifier: Operating System :: OS Independent
Requires-Python: >=3.10
Requires-Dist: firegex==3.4.11
Dynamic: author
Dynamic: author-email
Dynamic: classifier
Dynamic: description
Dynamic: description-content-type
Dynamic: home-page
Dynamic: requires-dist
Dynamic: requires-python
Dynamic: summary
